{"version":"1.0","reports":[{"id":"RPT-202606032230","datetime":"2026-06-03T22:30:39+07:00","date_display":"03/06/2026","time_display":"22:30","instrument":"XAUUSD","archetype":"Báo cáo 4H – 22:30","price_current":"4444.86","raw":{
  "instrument": "XAUUSD",
  "archetype": "Báo cáo 4H – 22:30",
  "timestamp": "2026-05-13T22:30:00+07:00",
  "summary": {
    "primary_bias": "Bearish",
    "bias_direction": "Bearish",
    "confidence_level": "Cao (75%+)",
    "current_price": 4444.86,
    "key_insight": "Vàng đang trong xu hướng giảm mạnh trên H4/H1/M15 với cấu trúc LH/LL rõ ràng. Giá đã phá vỡ vùng support quan trọng và hiện test lại 4445, tạo cơ hội bán kỹ thuật tốt.",
    "headline": "XAUUSD tiếp tục xu hướng giảm, target 4426 support"
  },
  "market_structure": {
    "D1": {
      "bias": "Bullish",
      "trend": "Xu hướng tăng dài hạn nhưng đang điều chỉnh",
      "structure": "Mixed Range",
      "ema_alignment": "Mixed",
      "rsi_zone": "Bearish Zone",
      "macd_bias": "Bearish",
      "key_levels": "Vùng 4540-4460 là khu vực quan trọng D1"
    },
    "H4": {
      "bias": "Bearish",
      "trend": "Xu hướng giảm rõ ràng với momentum mạnh",
      "structure": "LH/LL Bearish Structure đã xác lập",
      "ema_alignment": "Full Bearish Alignment",
      "rsi_zone": "Bearish Zone",
      "macd_bias": "Bearish",
      "momentum": "Expanding",
      "critical_levels": {
        "resistance": [4452.27, 4459.95],
        "support": [4439.54, 4426.21]
      }
    },
    "H1": {
      "bias": "Bearish",
      "trend": "Continuation của H4, momentum bearish mạnh",
      "intraday_story": "Giá test lại resistance 4445-4450 sau khi break support",
      "rsi_zone": "Bearish Zone",
      "macd_bias": "Bearish"
    },
    "M15": {
      "bias": "Bearish",
      "trend": "Bearish với cấu trúc LH/LL rõ ràng",
      "trigger_setup": "Doji pattern tại resistance cho entry bán",
      "structure": "LH/LL - Bearish Structure",
      "momentum": "Neutral",
      "candle_pattern": "Doji"
    }
  },
  "key_levels": {
    "current_price": 4444.86,
    "resistance": [4452.27, 4459.95],
    "support": [4439.54, 4426.21],
    "swing_high": 4468.18,
    "swing_low": 4426.21,
    "prev_day_high": 4541.45,
    "prev_day_low": 4463.06
  },
  "confluence_analysis": {
    "bullish_factors": ["D1 trend vẫn bullish", "Oversold potential tại support", "Volume tăng cho reversal"],
    "bearish_factors": ["H4/H1/M15 full bearish alignment", "Break key support 4450", "EMA bearish stack", "MACD negative momentum", "RSI trong bearish zone"],
    "dominant_bias": "Bearish"
  },
  "trading_scenarios": {
    "primary_scenario": {
      "bias": "Bearish",
      "setup": "Sell tại retest 4450-4452 hoặc current price với doji confirmation",
      "target": [4426.21, 4420.00],
      "stop_loss": 4460.00,
      "risk_reward": "1:2.0",
      "probability": 75
    },
    "alternative_scenario": {
      "bias": "Bearish",
      "setup": "Nếu break 4426 support, sell breakout",
      "target": [4410.00],
      "stop_loss": 4435.00,
      "risk_reward": "1:1.6",
      "probability": 65
    },
    "invalidation_scenario": {
      "bias": "Bullish",
      "setup": "Nếu reclaim 4460 với volume mạnh",
      "target": [4480.00],
      "stop_loss": 4440.00,
      "risk_reward": "1:1.8",
      "probability": 25
    }
  },
  "risk_factors": ["News volatility có thể đảo chiều đột ngột", "Support 4426 khá mạnh có thể tạo bounce", "D1 vẫn bullish bias"],
  "catalyst_watch": ["US Dollar strength", "Gold demand from Asia session"],
  "execution_plan": {
    "entry_zone": "4450-4452 resistance retest",
    "entry_condition": "Bearish confirmation candle tại resistance",
    "position_sizing": "0.5% risk per trade",
    "session_focus": "London/NY overlap",
    "key_time": "23:00-01:00 UTC+7"
  },
  "action_checklist": {
    "immediate": ["Monitor 4450 resistance reaction", "Watch for volume confirmation"],
    "pre_trade": ["Confirm bearish candle pattern", "Check news calendar"],
    "monitoring": ["4426 support level", "RSI divergence signals"]
  },
  "dashboard_summary": "XAUUSD trong downtrend mạnh H4/H1/M15, target 4426 support. Entry tại retest 4450-4452.",
  "telegram_summary": "🥇 XAUUSD BEARISH: Sell 4450-4452 → Target 4426. SL 4460. RR 1:2. Confidence 75%. Bearish structure rõ ràng đa khung thời gian."
},"docx_url":""}]}