{"version":"1.0","reports":[{"id":"RPT-202604241815","datetime":"2026-04-24T18:15:30+07:00","date_display":"24/04/2026","time_display":"18:15","instrument":"USATECM2026","archetype":"Báo cáo 4H – 18:15","price_current":"27279.5","raw":{
  "instrument": "NQ/US100",
  "archetype": "Báo cáo 4H – 18:00",
  "timestamp": "2026-04-01T18:00:00+07:00",
  "summary": {
    "primary_bias": "Bullish",
    "bias_direction": "Bullish",
    "confidence_level": "Cao (75%+)",
    "current_price": 27279.5,
    "key_insight": "Nasdaq đang trong xu hướng tăng mạnh trên tất cả khung thời gian với cấu trúc HH/HL rõ ràng. RSI overbought toàn diện nhưng momentum vẫn expanding, cho thấy lực mua mạnh.",
    "headline": "NQ bullish alignment hoàn hảo, momentum expanding dù RSI overbought"
  },
  "market_structure": {
    "D1": {
      "bias": "Bullish",
      "trend": "Xu hướng tăng mạnh với Full Bullish EMA alignment",
      "structure": "HH/HL Bullish",
      "ema_alignment": "Full Bullish Alignment",
      "rsi_zone": "Overbought",
      "macd_bias": "Bullish",
      "key_levels": "Đã vượt qua vùng kháng cự 27000, hướng tới test 27400+"
    },
    "H4": {
      "bias": "Bullish",
      "trend": "Trend tăng mạnh với EMA alignment hoàn hảo",
      "structure": "Cấu trúc bullish với các đỉnh và đáy ngày càng cao",
      "ema_alignment": "Full Bullish",
      "rsi_zone": "Overbought",
      "macd_bias": "Bullish",
      "momentum": "Expanding",
      "critical_levels": {
        "resistance": [27350, 27400],
        "support": [27200, 27130]
      }
    },
    "H1": {
      "bias": "Bullish",
      "trend": "Duy trì xu hướng tăng mạnh",
      "intraday_story": "Giá liên tục tạo higher highs với volume cao, momentum chưa có dấu hiệu suy yếu",
      "rsi_zone": "Overbought",
      "macd_bias": "Bullish"
    },
    "M15": {
      "bias": "Bullish",
      "trend": "Bullish với cấu trúc HH/HL rõ ràng",
      "trigger_setup": "Pullback về vùng 27200-27130 để continuation long",
      "structure": "HH/HL - Bullish Structure",
      "momentum": "Expanding",
      "candle_pattern": "Bullish Engulfing"
    }
  },
  "key_levels": {
    "current_price": 27279.5,
    "resistance": [27306.5, 27350],
    "support": [27200, 27130.55],
    "swing_high": 27306.5,
    "swing_low": 27062.25,
    "prev_day_high": 27154.75,
    "prev_day_low": 26680.25
  },
  "confluence_analysis": {
    "bullish_factors": ["Full Bullish EMA alignment tất cả khung", "Bullish Engulfing pattern với high volume", "MACD histogram tăng mạnh (14.22)", "Cấu trúc HH/HL rõ ràng", "BB expansion cho thấy trending mạnh"],
    "bearish_factors": ["RSI overbought trên 78", "Giá xa EMA20 có thể pullback", "Volume ratio 2.6 có thể unsustainable"],
    "dominant_bias": "Bullish"
  },
  "trading_scenarios": {
    "primary_scenario": {
      "bias": "Bullish",
      "setup": "Long trên pullback về vùng 27200-27130 (EMA20) với confirmation candle",
      "target": [27350, 27400],
      "stop_loss": 27100,
      "risk_reward": "1:2.3",
      "probability": 75
    },
    "alternative_scenario": {
      "bias": "Bullish",
      "setup": "Breakout trên 27306.5 với volume confirmation cho momentum tiếp tục",
      "target": [27400],
      "stop_loss": 27250,
      "risk_reward": "1:1.8",
      "probability": 65
    },
    "invalidation_scenario": {
      "bias": "Bearish",
      "setup": "Break dưới 27100 (swing low gần nhất) với volume tăng",
      "target": [27000],
      "stop_loss": 27150,
      "risk_reward": "1:2",
      "probability": 20
    }
  },
  "risk_factors": ["RSI divergence có thể xuất hiện", "Overbought kéo dài có thể dẫn đến correction sâu", "Volume unsustainable ở mức cao"],
  "catalyst_watch": ["Tech earnings season", "Fed policy updates", "Economic data releases"],
  "execution_plan": {
    "entry_zone": "27200-27130 cho pullback long hoặc breakout 27306.5",
    "entry_condition": "Confirmation candle + volume support",
    "position_sizing": "Giảm size do RSI overbought, chờ pullback tốt hơn",
    "session_focus": "US session cho volume cao",
    "key_time": "18:00-22:00 US market hours"
  },
  "action_checklist": {
    "immediate": ["Monitor pullback về EMA20", "Watch cho RSI divergence"],
    "pre_trade": ["Confirm volume trên entry", "Set stop loss chặt do overbought"],
    "monitoring": ["Track RSI cho exit signals", "Monitor 27306.5 resistance break"]
  },
  "dashboard_summary": "NQ trong trend bullish mạnh với full alignment, RSI overbought nhưng momentum vẫn expanding. Chờ pullback về 27130-27200 để long.",
  "telegram_summary": "🚀 NQ bullish mạnh 27279! Full EMA align, momentum expanding. RSI overbought - chờ pullback 27130-27200 long target 27350-27400. SL 27100 RR 1:2.3"
},"docx_url":""}]}