{"version":"1.0","reports":[{"id":"RPT-202605271430","datetime":"2026-05-27T14:30:39+07:00","date_display":"27/05/2026","time_display":"14:30","instrument":"XAUUSD","archetype":"Báo cáo 4H – 14:30","price_current":"4486.24","raw":{
  "instrument": "XAUUSD",
  "archetype": "Báo cáo 4H – 14:30",
  "timestamp": "2025-01-11T14:30:00+07:00",
  "summary": {
    "primary_bias": "Bearish",
    "bias_direction": "Bearish",
    "confidence_level": "Cao (75%+)",
    "current_price": 4486.24,
    "key_insight": "Vàng đang trong xu hướng bearish đa khung mạnh với H4, H1, M15 cùng hướng giảm. Giá nằm dưới tất cả EMA chính và RSI ở vùng bearish zone.",
    "headline": "XAUUSD bearish alignment mạnh - test support 4480"
  },
  "market_structure": {
    "D1": {
      "bias": "Neutral",
      "trend": "Xu hướng dài hạn bullish nhưng đang gặp sức ép điều chỉnh",
      "structure": "Mixed Range",
      "ema_alignment": "Mixed",
      "rsi_zone": "Bearish Zone",
      "macd_bias": "Bearish",
      "key_levels": "Vùng quan trọng 4580-4483 với bias ngắn hạn bearish"
    },
    "H4": {
      "bias": "Bearish",
      "trend": "Xu hướng giảm rõ ràng với EMA alignment bearish hoàn toàn",
      "structure": "LH/LL Bearish",
      "ema_alignment": "Full Bearish",
      "rsi_zone": "Bearish Zone",
      "macd_bias": "Bearish",
      "momentum": "Weakening",
      "critical_levels": {
        "resistance": [4496.55, 4503.88],
        "support": [4480.13, 4479.66]
      }
    },
    "H1": {
      "bias": "Bearish",
      "trend": "Tiếp tục xu hướng giảm từ H4",
      "intraday_story": "Áp lực bán tiếp tục từ các khung lớn",
      "rsi_zone": "Bearish Zone",
      "macd_bias": "Bearish"
    },
    "M15": {
      "bias": "Bearish",
      "trend": "Bearish với cấu trúc tích cực nhưng momentum nén lại",
      "trigger_setup": "Test support 4480 với volume bình thường",
      "structure": "HH/HL - Bullish Structure",
      "momentum": "Neutral",
      "candle_pattern": "None"
    }
  },
  "key_levels": {
    "current_price": 4486.24,
    "resistance": [4496.55, 4503.88],
    "support": [4480.13, 4479.66],
    "swing_high": 4517.1,
    "swing_low": 4495.84,
    "prev_day_high": 4580.65,
    "prev_day_low": 4482.74
  },
  "confluence_analysis": {
    "bullish_factors": ["M15 structure vẫn HH/HL", "Volume bình thường không panic", "Gần vùng support 4480"],
    "bearish_factors": ["H4-H1-M15 cùng bias bearish", "Full bearish EMA alignment H4", "RSI bearish zone đa khung", "MACD histogram âm tăng"],
    "dominant_bias": "Bearish"
  },
  "trading_scenarios": {
    "primary_scenario": {
      "bias": "Bearish",
      "setup": "Break support 4480 với volume tăng, target vùng 4470-4460",
      "target": [4470, 4460],
      "stop_loss": 4495,
      "risk_reward": "1:2.2",
      "probability": 75
    },
    "alternative_scenario": {
      "bias": "Bullish",
      "setup": "Bounce từ support 4480, retest EMA20 4496",
      "target": [4496],
      "stop_loss": 4475,
      "risk_reward": "1:1.5",
      "probability": 20
    },
    "invalidation_scenario": {
      "bias": "Bullish",
      "setup": "Break trên EMA50 4503 với volume mạnh",
      "target": [4517],
      "stop_loss": 4480,
      "risk_reward": "1:1.4",
      "probability": 5
    }
  },
  "risk_factors": ["News kinh tế Mỹ buổi chiều", "Áp lực từ DXY tăng mạnh", "Volume thấp có thể tạo fake breakout"],
  "catalyst_watch": ["US Inflation Data", "Fed officials speech"],
  "execution_plan": {
    "entry_zone": "4480-4485 cho short, 4478-4480 cho bounce long",
    "entry_condition": "Break 4480 với candle confirmation hoặc bounce với wick rejection",
    "position_sizing": "Conservative 1-2% risk do momentum nén",
    "session_focus": "US session 21:30-01:30",
    "key_time": "21:30 US inflation release"
  },
  "action_checklist": {
    "immediate": ["Monitor 4480 support reaction", "Watch volume expansion on break"],
    "pre_trade": ["Confirm H1 bearish structure", "Check news calendar"],
    "monitoring": ["RSI divergence signals", "EMA20 reclaim strength"]
  },
  "dashboard_summary": "XAUUSD trong bias bearish mạnh đa khung, test critical support 4480 với setup short ưu tiên.",
  "telegram_summary": "🥇XAUUSD: Bearish strong | Test support 4480 | Target 4470-4460 nếu break | SL 4495 | RR 1:2.2 ⚠️"
},"docx_url":""}]}