{"version":"1.0","reports":[{"id":"RPT-202604212230","datetime":"2026-04-21T22:30:34+07:00","date_display":"21/04/2026","time_display":"22:30","instrument":"XAUUSD","archetype":"Báo cáo 4H – 22:30","price_current":"4742.65","raw":{
  "instrument": "XAUUSD",
  "archetype": "Báo cáo 4H – 22:30",
  "timestamp": "2026-04-24T22:30:00+07:00",
  "summary": {
    "primary_bias": "Bearish",
    "bias_direction": "Bearish",
    "confidence_level": "Cao (75%+)",
    "current_price": 4742.65,
    "key_insight": "Vàng đang trong xu hướng giảm mạnh với H4, H1, M15 đồng loạt bearish. Price action tạo Bearish Pin Bar trên M15 với RSI oversold trên H1 cho thấy áp lực bán tiếp tục.",
    "headline": "XAUUSD bearish momentum mạnh, test vùng support 4740"
  },
  "market_structure": {
    "D1": {
      "bias": "Bullish",
      "trend": "Xu hướng tăng dài hạn nhưng đang có dấu hiệu điều chỉnh",
      "structure": "Mixed Range",
      "ema_alignment": "Mixed",
      "rsi_zone": "Neutral",
      "macd_bias": "Bullish",
      "key_levels": "Vùng 4820-4740 là range quan trọng trên D1"
    },
    "H4": {
      "bias": "Bearish",
      "trend": "Xu hướng giảm ngắn hạn trong điều chỉnh",
      "structure": "LH/LL Bearish",
      "ema_alignment": "Mixed",
      "rsi_zone": "Bearish Zone",
      "macd_bias": "Bearish",
      "momentum": "Expanding",
      "critical_levels": {
        "resistance": [4769.22, 4781.8],
        "support": [4740.62, 4723.82]
      }
    },
    "H1": {
      "bias": "Bearish",
      "trend": "Giảm mạnh với momentum bearish",
      "intraday_story": "Price action giảm liên tục từ vùng 4780 xuống test support 4740",
      "rsi_zone": "Oversold",
      "macd_bias": "Bearish"
    },
    "M15": {
      "bias": "Bearish",
      "trend": "Bearish với Full EMA Alignment",
      "trigger_setup": "Bearish Pin Bar rejection tại resistance 4757",
      "structure": "Mixed/Range Structure",
      "momentum": "Expanding",
      "candle_pattern": "Bearish Pin Bar"
    }
  },
  "key_levels": {
    "current_price": 4742.65,
    "resistance": [4769.22, 4781.8],
    "support": [4740.62, 4723.82],
    "swing_high": 4794.25,
    "swing_low": 4775.84,
    "prev_day_high": 4827.68,
    "prev_day_low": 4737.08
  },
  "confluence_analysis": {
    "bullish_factors": ["D1 MACD vẫn bullish", "H1 RSI oversold có thể bounce", "Price gần BB lower band"],
    "bearish_factors": ["H4/H1/M15 đồng loạt bearish", "Full bearish EMA alignment trên M15", "Bearish Pin Bar rejection", "MACD histogram âm mở rộng"],
    "dominant_bias": "Bearish"
  },
  "trading_scenarios": {
    "primary_scenario": {
      "bias": "Bearish",
      "setup": "Break below 4740 support với volume confirmation",
      "target": [4723.82, 4710.00],
      "stop_loss": 4755.00,
      "risk_reward": "1:2.2",
      "probability": 75
    },
    "alternative_scenario": {
      "bias": "Bearish",
      "setup": "Retest 4750-4755 resistance để short",
      "target": [4735.00],
      "stop_loss": 4765.00,
      "risk_reward": "1:1.5",
      "probability": 60
    },
    "invalidation_scenario": {
      "bias": "Bullish",
      "setup": "Reclaim above 4770 với strong momentum",
      "target": [4785.00],
      "stop_loss": 4740.00,
      "risk_reward": "1:1.5",
      "probability": 25
    }
  },
  "risk_factors": ["RSI H1 oversold có thể gây bounce ngắn hạn", "D1 bias vẫn bullish tạo conflict", "Volume thấp có thể thiếu confirmation"],
  "catalyst_watch": ["Phản ứng tại support 4740", "USD strength continuation"],
  "execution_plan": {
    "entry_zone": "4740-4745 break hoặc 4750-4755 retest",
    "entry_condition": "Bearish confirmation candle với volume",
    "position_sizing": "Conservative do conflict D1 vs intraday",
    "session_focus": "Asian/London session",
    "key_time": "Theo dõi break 4740 trong 1-2H tới"
  },
  "action_checklist": {
    "immediate": ["Monitor 4740 support level", "Watch for volume confirmation on break"],
    "pre_trade": ["Confirm bearish structure continuation", "Check USD correlation"],
    "monitoring": ["RSI divergence signs", "Volume expansion on moves"]
  },
  "dashboard_summary": "XAUUSD bearish momentum cao với 3 khung nhỏ cùng hướng, target test 4723 nếu break 4740",
  "telegram_summary": "🥇 XAUUSD Bearish setup mạnh! Target 4723-4710 nếu break 4740. SL 4755. Theo dõi volume confirmation. RR 1:2.2"
},"docx_url":""}]}