{"version":"1.0","reports":[{"id":"RPT-202604151815","datetime":"2026-04-15T18:15:31+07:00","date_display":"15/04/2026","time_display":"18:15","instrument":"XAUUSD","archetype":"Báo cáo 4H – 18:15","price_current":"25995.25","raw":{
  "instrument": "NQ/US100",
  "archetype": "Báo cáo 4H – 18:00",
  "timestamp": "2026-04-10T18:00:00+07:00",
  "summary": {
    "primary_bias": "Bullish",
    "bias_direction": "Bullish",
    "confidence_level": "Trung bình (50-74%)",
    "current_price": 25995.25,
    "key_insight": "Nasdaq duy trì xu hướng bullish đa khung với D1-H4 đồng thuận, tuy nhiên momentum M15 suy yếu và MACD bearish divergence gây thận trọng. Giá đang test vùng kháng cự 26000.",
    "headline": "NQ bullish bias nhưng cần chờ xác nhận breakout trên 26000"
  },
  "market_structure": {
    "D1": {
      "bias": "Bullish",
      "trend": "Xu hướng tăng mạnh với EMA alignment hoàn hảo",
      "structure": "HH/HL Bullish",
      "ema_alignment": "Full Bullish Alignment",
      "rsi_zone": "Bullish Zone",
      "macd_bias": "Bullish",
      "key_levels": "Vùng hỗ trợ mạnh tại EMA200 (25719), kháng cự tiếp theo 26100"
    },
    "H4": {
      "bias": "Bullish",
      "trend": "Bullish trend với momentum mạnh",
      "structure": "Higher highs đang hình thành",
      "ema_alignment": "Full Bullish Alignment",
      "rsi_zone": "Overbought",
      "macd_bias": "Bullish",
      "momentum": "Expanding",
      "critical_levels": {
        "resistance": [26037.25, 26056],
        "support": [25969.5, 25932.5]
      }
    },
    "H1": {
      "bias": "Bullish",
      "trend": "Tiếp tục xu hướng tăng nhưng có dấu hiệu điều chỉnh",
      "intraday_story": "Giá consolidate quanh vùng 26000, chờ breakout hoặc pullback",
      "rsi_zone": "Bullish Zone",
      "macd_bias": "Bearish"
    },
    "M15": {
      "bias": "Bullish",
      "trend": "Bullish nhưng momentum suy yếu",
      "trigger_setup": "Bullish Pin Bar tại vùng hỗ trợ EMA20 (25990)",
      "structure": "Mixed/Range Structure",
      "momentum": "Weakening",
      "candle_pattern": "Bullish Pin Bar"
    }
  },
  "key_levels": {
    "current_price": 25995.25,
    "resistance": [26037.25, 26056],
    "support": [25969.5, 25932.5],
    "swing_high": 26037.25,
    "swing_low": 25969.5,
    "prev_day_high": 26001.5,
    "prev_day_low": 25557.75
  },
  "confluence_analysis": {
    "bullish_factors": ["D1-H4 full bullish EMA alignment", "Higher highs structure trên H4", "Bullish Pin Bar setup M15", "RSI D1 trong vùng bullish zone"],
    "bearish_factors": ["H1-M15 MACD bearish divergence", "H4 RSI overbought", "Momentum M15 suy yếu", "Giá gặp kháng cự tại swing high"],
    "dominant_bias": "Bullish"
  },
  "trading_scenarios": {
    "primary_scenario": {
      "bias": "Bullish",
      "setup": "Breakout trên 26037 với volume xác nhận, target extension bullish",
      "target": [26080, 26120],
      "stop_loss": 25969,
      "risk_reward": "1:2.2",
      "probability": 65
    },
    "alternative_scenario": {
      "bias": "Bullish",
      "setup": "Pullback về EMA50 (25976) tạo higher low, long từ vùng support",
      "target": [26030],
      "stop_loss": 25950,
      "risk_reward": "1:2.1",
      "probability": 25
    },
    "invalidation_scenario": {
      "bias": "Bearish",
      "setup": "Break dưới 25969 với volume, momentum shift bearish",
      "target": [25920],
      "stop_loss": 26000,
      "risk_reward": "1:1.6",
      "probability": 10
    }
  },
  "risk_factors": ["MACD bearish divergence M15-H1", "RSI H4 overbought có thể gây pullback", "Volume thấp có thể không sustain breakout"],
  "catalyst_watch": ["US economic data release", "Fed policy signals"],
  "execution_plan": {
    "entry_zone": "25990-26000 (current area) hoặc pullback 25975-25980",
    "entry_condition": "Bullish confirmation trên 26037 hoặc bounce từ EMA support",
    "position_sizing": "Moderate 1-2% risk do mixed signals M15",
    "session_focus": "US session opening, European close overlap",
    "key_time": "18:00-20:00 GMT+7 volume expansion"
  },
  "action_checklist": {
    "immediate": ["Monitor 26037 breakout level", "Watch volume confirmation"],
    "pre_trade": ["Confirm EMA20 holding support", "Check MACD histogram turning positive"],
    "monitoring": ["Track RSI divergence resolution", "Monitor 25969 support integrity"]
  },
  "dashboard_summary": "NQ bullish bias với D1-H4 alignment mạnh, chờ xác nhận breakout 26037 hoặc long từ pullback support.",
  "telegram_summary": "🟢 NQ BULLISH | 25995.25 ⚡ Chờ break 26037→26080+ hoặc long pullback 25975 | SL: 25969 | Momentum suy yếu cần theo dõi"
},"docx_url":""}]}